savetext.py
wx_send.py
wxPush-2.0.dist-info/METADATA
wxPush-2.0.dist-info/WHEEL
wxPush-2.0.dist-info/top_level.txt
wxPush-2.0.dist-info/RECORD
